{
  "data": {
    "setting": {
      "data": {
        "id": "1",
        "attributes": {
          "blogName": "Blog Name Medicina",
          "blogDescription": "Teste blog de medicina",
          "logo": {
            "data": {
              "id": "5",
              "attributes": {
                "url": "https://res.cloudinary.com/unidavi/image/upload/v1662040134/capalancamentomedicina_83583e2a49.jpg"
              }
            }
          },
          "menuLink": [
            {
              "id": "1",
              "link": "https://mentor.unidavi.edu.br/unidaviMentorWebG5/jsf/dashboard.jsf?sourcedhb=201",
              "text": "text",
              "newTab": true
            },
            {
              "id": "2",
              "link": "#link",
              "text": "O Link  2",
              "newTab": true
            }
          ]
        }
      }
    },
    "posts": {
      "data": [
        {
          "attributes": {
            "title": "teste2"
          }
        },
        {
          "attributes": {
            "title": "teste"
          }
        },
        {
          "attributes": {
            "title": "teste3"
          }
        }
      ]
    }
  }
}
